MANIFEST.in
README.md
dev-requirements.txt
netuitive-statsd
requirements.txt
setup.cfg
setup.py
libs/__init__.py
libs/config.py
libs/daemon.py
libs/elements.py
libs/log.py
libs/poster.py
libs/server.py
libs/service.py
libs/statsd/__init__.py
libs/statsd/counter.py
libs/statsd/gauge.py
libs/statsd/histogram.py
libs/statsd/parser.py
libs/statsd/set.py
libs/statsd/util.py
netuitive_statsd.egg-info/PKG-INFO
netuitive_statsd.egg-info/SOURCES.txt
netuitive_statsd.egg-info/dependency_links.txt
netuitive_statsd.egg-info/not-zip-safe
netuitive_statsd.egg-info/requires.txt
netuitive_statsd.egg-info/top_level.txt