Metadata-Version: 1.1
Name: netuitive-statsd
Version: 0.4.0
Summary: Netuitive StatsD server
Home-page: https://github.com/netuitive/netuitive-statsd
Author: Netuitive
Author-email: python@netuitive.com
License: Apache License 2.0
Keywords: netuitive netuitive-statsd
Platform: UNKNOWN
Classifier: Development Status :: 2 - Pre-Alpha
Classifier: Intended Audience :: Developers
Classifier: License :: OSI Approved :: Apache Software License
Classifier: Topic :: Software Development :: Libraries :: Python Modules
Classifier: Natural Language :: English
Classifier: Programming Language :: Python :: 2.7
Classifier: Programming Language :: Python :: 3.3
Classifier: Programming Language :: Python :: 3.4
Classifier: Programming Language :: Python :: 3.5
